[
 {
  "id": "b44265c4-3dd1-4c6d-b33e-5f70763adbe8",
  "details": {
   "id": "8bb79bbe-1802-511e-80de-6117e48c671c",
   "name": "Grappler",
   "description": "You've developed the skills necessary to hold your own in close-quarters grappling. You gain the following benefits:\n\n- You have advantage on attack rolls against a creature you are grappling.\n- You can use your action to try to pin a creature grappled by you. To do so, make another grapple check. If you succeed, you and the creature are both restrained until the grapple ends.",
   "metadata": {
    "mads": [
     {
      "command": "AddAdvantage",
      "value": {
       "rollType": "WeaponAttack",
       "mode": "advantage",
       "condition": "against a creature you are grappling"
      },
      "type": 0,
      "prerequisites": [],
      "group": 0
     }
    ]
   }
  },
  "prerequisites": [
   {
    "type": 7,
    "value": "STR 13"
   }
  ],
  "legacy": true
 }
]
